hasnain/__init__.py
hasnain/client.py
hasnain/dispatcher.py
hasnain/emoji.py
hasnain/file_id.py
hasnain/filters.py
hasnain/mime_types.py
hasnain/py.typed
hasnain/sync.py
hasnain/utils.py
hasnain/connection/__init__.py
hasnain/connection/connection.py
hasnain/connection/transport/__init__.py
hasnain/connection/transport/tcp/__init__.py
hasnain/connection/transport/tcp/tcp.py
hasnain/connection/transport/tcp/tcp_abridged.py
hasnain/connection/transport/tcp/tcp_abridged_o.py
hasnain/connection/transport/tcp/tcp_full.py
hasnain/connection/transport/tcp/tcp_intermediate.py
hasnain/connection/transport/tcp/tcp_intermediate_o.py
hasnain/crypto/__init__.py
hasnain/crypto/aes.py
hasnain/crypto/mtproto.py
hasnain/crypto/prime.py
hasnain/crypto/rsa.py
hasnain/enums/__init__.py
hasnain/enums/auto_name.py
hasnain/enums/chat_action.py
hasnain/enums/chat_event_action.py
hasnain/enums/chat_member_status.py
hasnain/enums/chat_members_filter.py
hasnain/enums/chat_type.py
hasnain/enums/message_entity_type.py
hasnain/enums/message_media_type.py
hasnain/enums/message_service_type.py
hasnain/enums/messages_filter.py
hasnain/enums/next_code_type.py
hasnain/enums/parse_mode.py
hasnain/enums/poll_type.py
hasnain/enums/sent_code_type.py
hasnain/enums/user_status.py
hasnain/errors/__init__.py
hasnain/errors/rpc_error.py
hasnain/handlers/__init__.py
hasnain/handlers/callback_query_handler.py
hasnain/handlers/chat_join_request_handler.py
hasnain/handlers/chat_member_updated_handler.py
hasnain/handlers/chosen_inline_result_handler.py
hasnain/handlers/deleted_messages_handler.py
hasnain/handlers/disconnect_handler.py
hasnain/handlers/edited_message_handler.py
hasnain/handlers/handler.py
hasnain/handlers/inline_query_handler.py
hasnain/handlers/message_handler.py
hasnain/handlers/poll_handler.py
hasnain/handlers/raw_update_handler.py
hasnain/handlers/user_status_handler.py
hasnain/methods/__init__.py
hasnain/methods/advanced/__init__.py
hasnain/methods/advanced/invoke.py
hasnain-3.4.dist-info/COPYING
hasnain-3.4.dist-info/COPYING.lesser
hasnain-3.4.dist-info/LICENSE
hasnain-3.4.dist-info/METADATA
hasnain-3.4.dist-info/NOTICE
hasnain-3.4.dist-info/WHEEL
hasnain-3.4.dist-info/top_level.txt
hasnain-3.4.dist-info/RECORD
